cuda_mock/ctypes_helper.py
cuda_mock/gpu_validation.py
cuda_mock/dynamic_obj.py
cuda_mock/cuda_mock_impl.py
cuda_mock/__init__.py
cuda_mock/libcuda_mock_impl.so
cuda_mock/PltHook.cmake
cuda_mock/libxpu_mock_improve.so
cuda_mock/triton_mock.py
cuda_mock/include/cuda_mock.h
cuda_mock/include/support.h
cuda_mock/include/macro.h
cuda_mock/include/hook.h
cuda_mock/include/cuda_types.h
cuda_mock/include/env_mgr.h
cuda_mock/include/xpu_mock.h
cuda_mock/include/elf_parser.h
cuda_mock/include/backtrace.h
cuda_mock/include/hook_context.h
cuda_mock/include/util.h
cuda_mock/include/env_util.h
cuda_mock/include/GlobalVarMgr.h
cuda_mock/include/fmt/color.h
cuda_mock/include/fmt/xchar.h
cuda_mock/include/fmt/core.h
cuda_mock/include/fmt/ranges.h
cuda_mock/include/fmt/ostream.h
cuda_mock/include/fmt/printf.h
cuda_mock/include/fmt/format.h
cuda_mock/include/fmt/compile.h
cuda_mock/include/fmt/os.h
cuda_mock/include/fmt/format-inl.h
cuda_mock/include/fmt/chrono.h
cuda_mock/include/fmt/std.h
cuda_mock/include/fmt/args.h
cuda_mock/include/profile/timer.h
cuda_mock/include/logger/logger_stl.h
cuda_mock/include/logger/logger.h
cuda_mock/include/logger/StringRef.h
cuda_mock-1.1.3.dist-info/top_level.txt
cuda_mock-1.1.3.dist-info/RECORD
cuda_mock-1.1.3.dist-info/LICENSE
cuda_mock-1.1.3.dist-info/METADATA
cuda_mock-1.1.3.dist-info/WHEEL
