Metadata-Version: 2.1
Name: cuda-mock
Version: 1.1.3
Summary: mock cuda runtime api
Home-page: https://github.com/lipracer/torch-cuda-mock
Author: lipracer
Author-email: lipracer <lipracer@gmail.com>
License: BSD-3-Clause
Requires-Python: >=3.8
License-File: LICENSE
